sdk/__init__.py
sdk/accounts.py
sdk/companies.py
sdk/people.py
sdk/sdk.py
sdk/sdkconfiguration.py
sdk/user.py
sdk/models/__init__.py
sdk/models/operations/__init__.py
sdk/models/operations/enrich_company.py
sdk/models/operations/enrich_person.py
sdk/models/operations/list_employees.py
sdk/models/operations/list_jobs.py
sdk/models/operations/list_users.py
sdk/models/operations/login.py
sdk/models/operations/me.py
sdk/models/operations/search_companies.py
sdk/models/operations/search_people.py
sdk/models/shared/__init__.py
sdk/models/shared/account.py
sdk/models/shared/company.py
sdk/models/shared/person.py
sdk/models/shared/security.py
sdk/utils/__init__.py
sdk/utils/retries.py
sdk/utils/utils.py
structure_py-0.18.1.dist-info/LICENSE.md
structure_py-0.18.1.dist-info/METADATA
structure_py-0.18.1.dist-info/WHEEL
structure_py-0.18.1.dist-info/top_level.txt
structure_py-0.18.1.dist-info/RECORD
